LICENSE
MANIFEST.in
README.md
requirements.txt
setup.py
kline_timestamp/__init__.py
kline_timestamp/kline_timestamp.py
kline_timestamp.egg-info/PKG-INFO
kline_timestamp.egg-info/SOURCES.txt
kline_timestamp.egg-info/dependency_links.txt
kline_timestamp.egg-info/requires.txt
kline_timestamp.egg-info/top_level.txt