Metadata-Version: 2.1
Name: kline-timestamp
Version: 0.1.4
Summary: KlineTimestamp is a Python library designed to efficiently handle timestamps within discrete time intervals, commonly known as klines or candlesticks, often used in financial data analysis.
Home-page: https://github.com/nand0san/kline_timestamp
Author: nand0san
Author-email: 
Classifier: Programming Language :: Python :: 3
Classifier: License :: OSI Approved :: MIT License
Classifier: Operating System :: OS Independent
Requires-Python: >=3.6
License-File: LICENSE
